newrelic_grep/cli_nrgrep.py
newrelic_grep/nrgrep.py
newrelic_grep/py.typed
newrelic_grep-1.0.2.dist-info/LICENSE
newrelic_grep-1.0.2.dist-info/METADATA
newrelic_grep-1.0.2.dist-info/WHEEL
newrelic_grep-1.0.2.dist-info/entry_points.txt
newrelic_grep-1.0.2.dist-info/RECORD
