Metadata-Version: 2.1
Name: newrelic-grep
Version: 1.0.2
Summary: grep command for New Relic
Home-page: https://github.com/hirachan/newrelic-grep
Author: HIRANO Yoshitaka
Author-email: yo@hirano.cc
Requires-Python: >=3.7,<4.0
Classifier: Programming Language :: Python :: 3
Classifier: Programming Language :: Python :: 3.7
Classifier: Programming Language :: Python :: 3.8
Classifier: Programming Language :: Python :: 3.9
Classifier: Programming Language :: Python :: 3.10
Classifier: Programming Language :: Python :: 3.11
Requires-Dist: requests (>=2.28.2,<3.0.0)
Requires-Dist: types-requests (>=2.28.11.15,<3.0.0.0)
